ufolint/__init__.py
ufolint/app.py
ufolint/settings.py
ufolint/controllers/__init__.py
ufolint/controllers/runner.py
ufolint/data/__init__.py
ufolint/data/tstobj.py
ufolint/data/ufo.py
ufolint/stdoutput/__init__.py
ufolint/utilities/__init__.py
ufolint/validators/__init__.py
ufolint/validators/glifvalidators.py
ufolint/validators/imagesvalidators.py
ufolint/validators/plistvalidators.py
ufolint/validators/typevalidators.py
ufolint/validators/xmlvalidators.py
ufolint-1.2.0.dist-info/LICENSE
ufolint-1.2.0.dist-info/METADATA
ufolint-1.2.0.dist-info/WHEEL
ufolint-1.2.0.dist-info/entry_points.txt
ufolint-1.2.0.dist-info/top_level.txt
ufolint-1.2.0.dist-info/RECORD
