Metadata-Version: 2.1
Name: ufolint
Version: 1.2.0
Summary: UFO source file linter
Home-page: https://github.com/source-foundry/ufolint
Author: Christopher Simpkins
Author-email: chris@sourcefoundry.org
License: MIT license
Platform: any
Classifier: Development Status :: 5 - Production/Stable
Classifier: Natural Language :: English
Classifier: License :: OSI Approved :: MIT License
Classifier: Operating System :: OS Independent
Classifier: Programming Language :: Python
Classifier: Programming Language :: Python :: 3
Classifier: Programming Language :: Python :: 3.6
Classifier: Programming Language :: Python :: 3.7
Classifier: Programming Language :: Python :: 3.8
Classifier: Programming Language :: Python :: 3.9
Classifier: Topic :: Software Development :: Libraries :: Python Modules
Classifier: Topic :: Text Processing :: Fonts
Requires-Python: >=3.6.0
Provides-Extra: dev
